huaweicloudsdkapig/__init__.py
huaweicloudsdkapig/v2/__init__.py
huaweicloudsdkapig/v2/apig_async_client.py
huaweicloudsdkapig/v2/apig_client.py
huaweicloudsdkapig/v2/model/__init__.py
huaweicloudsdkapig/v2/model/accept_or_reject_endpoint_connections_request.py
huaweicloudsdkapig/v2/model/accept_or_reject_endpoint_connections_response.py
huaweicloudsdkapig/v2/model/acl_api_binding_create.py
huaweicloudsdkapig/v2/model/acl_api_binding_info.py
huaweicloudsdkapig/v2/model/acl_batch_delete.py
huaweicloudsdkapig/v2/model/acl_batch_result_failure_resp.py
huaweicloudsdkapig/v2/model/acl_bind_api_info.py
huaweicloudsdkapig/v2/model/acl_binding_batch_delete.py
huaweicloudsdkapig/v2/model/acl_binding_batch_failure.py
huaweicloudsdkapig/v2/model/add_custom_ingress_port_request.py
huaweicloudsdkapig/v2/model/add_custom_ingress_port_response.py
huaweicloudsdkapig/v2/model/add_eip_v2_request.py
huaweicloudsdkapig/v2/model/add_eip_v2_response.py
huaweicloudsdkapig/v2/model/add_endpoint_permissions_request.py
huaweicloudsdkapig/v2/model/add_endpoint_permissions_response.py
huaweicloudsdkapig/v2/model/add_engress_eip_v2_request.py
huaweicloudsdkapig/v2/model/add_engress_eip_v2_response.py
huaweicloudsdkapig/v2/model/add_ingress_eip_v2_request.py
huaweicloudsdkapig/v2/model/add_ingress_eip_v2_response.py
huaweicloudsdkapig/v2/model/adding_backend_instances_v2_request.py
huaweicloudsdkapig/v2/model/adding_backend_instances_v2_response.py
huaweicloudsdkapig/v2/model/api_acl_create.py
huaweicloudsdkapig/v2/model/api_acl_info_with_bind_num.py
huaweicloudsdkapig/v2/model/api_action_info.py
huaweicloudsdkapig/v2/model/api_auth_base.py
huaweicloudsdkapig/v2/model/api_auth_create.py
huaweicloudsdkapig/v2/model/api_auth_info.py
huaweicloudsdkapig/v2/model/api_auth_relations.py
huaweicloudsdkapig/v2/model/api_backend_vpc_req.py
huaweicloudsdkapig/v2/model/api_base_info.py
huaweicloudsdkapig/v2/model/api_batch_publish.py
huaweicloudsdkapig/v2/model/api_bind_acl_info.py
huaweicloudsdkapig-3.1.184.dist-info/METADATA
huaweicloudsdkapig-3.1.184.dist-info/WHEEL
huaweicloudsdkapig-3.1.184.dist-info/licenses/LICENSE
huaweicloudsdkapig-3.1.184.dist-info/RECORD
